topsis/__init__.py
topsis/topsis.py
topsis_priyal_102303563-0.0.2.dist-info/licenses/LICENSE
topsis_priyal_102303563-0.0.2.dist-info/METADATA
topsis_priyal_102303563-0.0.2.dist-info/WHEEL
topsis_priyal_102303563-0.0.2.dist-info/entry_points.txt
topsis_priyal_102303563-0.0.2.dist-info/top_level.txt
topsis_priyal_102303563-0.0.2.dist-info/RECORD
