Metadata-Version: 2.4
Name: Topsis-Priyal-102303563
Version: 0.0.2
Summary: TOPSIS implementation for multi-criteria decision making
Author: Priyal Gupta
License: MIT
License-File: LICENSE
Requires-Dist: pandas
Requires-Dist: numpy
Dynamic: author
Dynamic: description
Dynamic: description-content-type
Dynamic: license
Dynamic: license-file
Dynamic: requires-dist
Dynamic: summary
